{
	"total": 20,
  "data": [
    {
    	"cztime":"1",
      "czservice": "21321",
      "czaccount": "2016-12-31",
      "czgameid": "12",
      "czcard": "2256",
      "czordernumber": "04"
    },
    {
    	"cztime":"1",
      "czservice": "21321",
      "czaccount": "2016-12-31",
      "czgameid": "12",
      "czcard": "2256",
      "czordernumber": "04"
    },
    {
    	"cztime":"1",
      "czservice": "21321",
      "czaccount": "2016-12-31",
      "czgameid": "12",
      "czcard": "2256",
      "czordernumber": "04"
    },
    {
    	"cztime":"1",
      "czservice": "21321",
      "czaccount": "2016-12-31",
      "czgameid": "12",
      "czcard": "2256",
      "czordernumber": "04"
    },
    {
    	"cztime":"1",
      "czservice": "21321",
      "czaccount": "2016-12-31",
      "czgameid": "12",
      "czcard": "2256",
      "czordernumber": "04"
    },
    {
    	"cztime":"1",
      "czservice": "21321",
      "czaccount": "2016-12-31",
      "czgameid": "12",
      "czcard": "2256",
      "czordernumber": "04"
    },
    {
    	"cztime":"1",
      "czservice": "21321",
      "czaccount": "2016-12-31",
      "czgameid": "12",
      "czcard": "2256",
      "czordernumber": "04"
    },
    {
    	"cztime":"1",
      "czservice": "21321",
      "czaccount": "2016-12-31",
      "czgameid": "12",
      "czcard": "2256",
      "czordernumber": "04"
    }
  ]
}